instagram_scraper/__init__.py
instagram_scraper/app.py
instagram_scraper/constants.py
instagram_scraper/tests/__init__.py
instagram_scraper/tests/test_instagram.py
instagram_scraper-1.11.0.dist-info/AUTHORS.md
instagram_scraper-1.11.0.dist-info/LICENSE.txt
instagram_scraper-1.11.0.dist-info/METADATA
instagram_scraper-1.11.0.dist-info/WHEEL
instagram_scraper-1.11.0.dist-info/entry_points.txt
instagram_scraper-1.11.0.dist-info/top_level.txt
instagram_scraper-1.11.0.dist-info/RECORD
