Metadata-Version: 2.1
Name: instagram-scraper
Version: 1.11.0
Summary: instagram-scraper is a command-line application written in Python that scrapes and downloads an instagram user's photos and videos. Use responsibly.
Home-page: https://github.com/arc298/instagram-scraper
Author: Richard Arcega
Author-email: hello@richardarcega.com
Maintainer: Alexander Nikolaev
Maintainer-email: alexander@nikolaev.expert
License: Public domain
Download-URL: https://github.com/arc298/instagram-scraper/tarball/1.11.0
Keywords: instagram,scraper,download,media,photos,videos
Platform: UNKNOWN
License-File: LICENSE.txt
License-File: AUTHORS.md
Requires-Dist: requests (>=2.18.4)
Requires-Dist: tqdm (>=3.8.0)
